odoo10_addon_web_widget_many2many_tags_multi_selection-10.0.1.0.0-py2.7-nspkg.pth
odoo/addons/web_widget_many2many_tags_multi_selection/README.rst
odoo/addons/web_widget_many2many_tags_multi_selection/__init__.py
odoo/addons/web_widget_many2many_tags_multi_selection/__manifest__.py
odoo/addons/web_widget_many2many_tags_multi_selection/static/description/icon.png
odoo/addons/web_widget_many2many_tags_multi_selection/static/src/js/view_form.js
odoo/addons/web_widget_many2many_tags_multi_selection/views/web_widget_many2many_tags_multi_selection.xml
odoo10_addon_web_widget_many2many_tags_multi_selection-10.0.1.0.0.dist-info/DESCRIPTION.rst
odoo10_addon_web_widget_many2many_tags_multi_selection-10.0.1.0.0.dist-info/METADATA
odoo10_addon_web_widget_many2many_tags_multi_selection-10.0.1.0.0.dist-info/RECORD
odoo10_addon_web_widget_many2many_tags_multi_selection-10.0.1.0.0.dist-info/WHEEL
odoo10_addon_web_widget_many2many_tags_multi_selection-10.0.1.0.0.dist-info/metadata.json
odoo10_addon_web_widget_many2many_tags_multi_selection-10.0.1.0.0.dist-info/namespace_packages.txt
odoo10_addon_web_widget_many2many_tags_multi_selection-10.0.1.0.0.dist-info/top_level.txt
