Metadata-Version: 2.0
Name: odoo10-addon-web-widget-many2many-tags-multi-selection
Version: 10.0.1.0.0
Summary: Tags multiple selection
Home-page: https://www.akretion.com
Author: Akretion, Odoo Community Association (OCA), Jamin Shah
Author-email: support@odoo-community.org
License: UNKNOWN
Platform: UNKNOWN
Classifier: Programming Language :: Python :: 2.7
Classifier: Framework :: Odoo
Requires-Dist: odoo (<10.1dev,>=10.0)
